clea/__init__.py
clea/context.py
clea/exceptions.py
clea/helpers.py
clea/params.py
clea/parser.py
clea/py.typed
clea/runner.py
clea/wrappers.py
clea-0.1.0rc3.dist-info/LICENSE
clea-0.1.0rc3.dist-info/METADATA
clea-0.1.0rc3.dist-info/WHEEL
clea-0.1.0rc3.dist-info/RECORD
