Metadata-Version: 2.1
Name: clea
Version: 0.1.0rc3
Summary: Framework for writing CLI application quickly
Author: angrybayblade
Author-email: vptl185@gmail.com
Requires-Python: >=3.8,<4.0
Classifier: Programming Language :: Python :: 3
Classifier: Programming Language :: Python :: 3.8
Classifier: Programming Language :: Python :: 3.9
Classifier: Programming Language :: Python :: 3.10
Classifier: Programming Language :: Python :: 3.11
Requires-Dist: typing-extensions (>=4.7.1,<5.0.0)
